LICENSE.rst
README.md
pyproject.toml
setup.py
tests/__init__.py
tests/common.py
tests/acceptance/__init__.py
tests/acceptance/test_artificial.py
tests/acceptance/test_dependencies.py
tests/acceptance/test_external_run_scripts.py
tests/lint/__init__.py
tests/lint/test_license.py
tests/lint/test_mypy.py
tests/lint/test_pycodestyle.py
tests/lint/test_pylint.py
tests/unit/__init__.py
tests/unit/non_utf8_printer.py
tests/unit/test_activehdl_interface.py
tests/unit/test_builtins.py
tests/unit/test_cds_file.py
tests/unit/test_check_preprocessor.py
tests/unit/test_configuration.py
tests/unit/test_csv_logs.py
tests/unit/test_database.py
tests/unit/test_dependency_graph.py
tests/unit/test_ghdl_interface.py
tests/unit/test_incisive_interface.py
tests/unit/test_location_preprocessor.py
tests/unit/test_modelsim_interface.py
tests/unit/test_ostools.py
tests/unit/test_project.py
tests/unit/test_rivierapro_interface.py
tests/unit/test_simulator_interface.py
tests/unit/test_test_bench.py
tests/unit/test_test_bench_list.py
tests/unit/test_test_report.py
tests/unit/test_test_runner.py
tests/unit/test_test_suites.py
tests/unit/test_tokenizer.py
tests/unit/test_ui.py
tests/unit/test_verilog_parser.py
tests/unit/test_verilog_preprocessor.py
tests/unit/test_verilog_tokenizer.py
tests/unit/test_vhdl_parser.py
tests/unit/test_vhdl_standard.py
vunit/__init__.py
vunit/about.py
vunit/builtins.py
vunit/cached.py
vunit/check_preprocessor.py
vunit/color_printer.py
vunit/configuration.py
vunit/csv_logs.py
vunit/database.py
vunit/dependency_graph.py
vunit/design_unit.py
vunit/exceptions.py
vunit/hashing.py
vunit/json4vhdl.py
vunit/library.py
vunit/location_preprocessor.py
vunit/ostools.py
vunit/persistent_tcl_shell.py
vunit/project.py
vunit/source_file.py
vunit/verilog.py
vunit/version_check.py
vunit/vhdl_parser.py
vunit/vhdl_standard.py
vunit/vunit_cli.py
vunit/com/__init__.py
vunit/com/codec_datatype_template.py
vunit/com/codec_generator.py
vunit/com/codec_vhdl_array_type.py
vunit_hdl.egg-info/PKG-INFO
vunit_hdl.egg-info/SOURCES.txt
vunit_hdl.egg-info/dependency_links.txt
vunit_hdl.egg-info/not-zip-safe
vunit_hdl.egg-info/requires.txt
vunit_hdl.egg-info/top_level.txt