Metadata-Version: 2.1
Name: vunit-hdl
Version: 4.7.0
Summary: VUnit is an open source unit testing framework for VHDL/SystemVerilog.
Home-page: https://github.com/VUnit/vunit
Author: Lars Asplund
Author-email: lars.anders.asplund@gmail.com
License: Mozilla Public License 2.0 (MPL 2.0)
Classifier: Development Status :: 5 - Production/Stable
Classifier: License :: OSI Approved :: Mozilla Public License 2.0 (MPL 2.0)
Classifier: Natural Language :: English
Classifier: Intended Audience :: Developers
Classifier: Programming Language :: Python :: 3.6
Classifier: Programming Language :: Python :: 3.7
Classifier: Programming Language :: Python :: 3.8
Classifier: Programming Language :: Python :: 3.9
Classifier: Programming Language :: Python :: 3.10
Classifier: Operating System :: Microsoft :: Windows
Classifier: Operating System :: MacOS :: MacOS X
Classifier: Operating System :: POSIX :: Linux
Classifier: Topic :: Software Development :: Testing
Classifier: Topic :: Scientific/Engineering :: Electronic Design Automation (EDA)
Requires: colorama
Requires-Python: >=3.6
License-File: LICENSE.rst
